{
  "assembly_id": 20,
  "bill_id": "2001398",
  "title": "[2001398] 국세기본법 일부개정법률안(김현미의원 등 11인) 입법예고중",
  "current_status": "위원회 심사",
  "reception_info": [
    "2001398",
    "2016-08-03",
    "김현미의원 등 11인",
    "의안원문",
    "제20대 (2016~2020) 제344회"
  ],
  "reception_file_link": "javascript:openBillFile('http://likms.assembly.go.kr/filegate/servlet/FileGate','CE37B377-A01E-80CF-8B7C-46503A45006A','0');",
  "proposers": [
    {
      "name_kr": "김현미",
      "party": "더불어민주당",
      "name_cn": "金賢美"
    },
    {
      "name_kr": "김해영",
      "party": "더불어민주당",
      "name_cn": "金海永"
    },
    {
      "name_kr": "민병두",
      "party": "더불어민주당",
      "name_cn": "閔丙두"
    },
    {
      "name_kr": "박광온",
      "party": "더불어민주당",
      "name_cn": "朴洸瑥"
    },
    {
      "name_kr": "박남춘",
      "party": "더불어민주당",
      "name_cn": "朴南春"
    },
    {
      "name_kr": "송옥주",
      "party": "더불어민주당",
      "name_cn": "宋玉珠"
    },
    {
      "name_kr": "윤후덕",
      "party": "더불어민주당",
      "name_cn": "尹厚德"
    },
    {
      "name_kr": "인재근",
      "party": "더불어민주당",
      "name_cn": "印在謹"
    },
    {
      "name_kr": "진선미",
      "party": "더불어민주당",
      "name_cn": "陳善美"
    },
    {
      "name_kr": "채이배",
      "party": "국민의당",
      "name_cn": "蔡利培"
    },
    {
      "name_kr": "황주홍",
      "party": "국민의당",
      "name_cn": "黃柱洪"
    }
  ],
  "summaries": [
    "\n제안이유 및 주요내용\n\n  현행법은 해외이주자의 국내재산 상속등기 지연에 따른 국세부과제척기간을 연장하지 않고 있는 상황임. 따라서 해외이주자 등의 사망에도 불구하고 상속세 등 조세회피 목적으로 장기간 명의를 변경하지 않는 경우 국세부과제척기간(15년)이 도과하여 조세일실 우려의 의견이 제기되고 있음. \n  또한, 상속세 국세부과제척기간 특례에서 50억원 이하 재산은 적용하지 않고 있음. 하지만 상속·증여세 최고세율(50%) 구간이 30억원 이상이고, 조세범칙조사 대상 조세포탈 예상세액이 5억원 이상인 점 등을 고려할 때 현행 50억원에서 30억원으로 인하할 필요가 있는 상황임.\n  이에 상속세 및 증여세의 국세부과제척기간의 특례사유를 확대하고 적용가액을 인하하여 조세일실 우려를 낮추고자 함(안 제26조의 2).\n"
  ],
  "withdrawers": [],
  "proposed_date": "2016-08-03",
  "decision_date": null,
  "link_id": "PRC_N1T6P0O8P0M3L1Q8S0T3W4K7T1J4V8",
  "proposer_type": "의원",
  "status": "처리"
}