{
  "assembly_id": 20,
  "bill_id": "2002796",
  "title": "[2002796] 재난 및 안전관리 기본법 일부개정법률안(윤재옥의원 등 10인) 입법예고중",
  "current_status": "대안반영폐기",
  "reception_info": [
    "2002796",
    "2016-10-21",
    "윤재옥의원 등 10인",
    "의안원문",
    "제20대 (2016~2020) 제346회"
  ],
  "reception_file_link": "javascript:openBillFile('http://likms.assembly.go.kr/filegate/servlet/FileGate','D5E6436A-40A1-E081-F5C6-7CFE7310BDBE','0');",
  "proposers": [
    {
      "name_kr": "윤재옥",
      "party": "새누리당",
      "name_cn": "尹在玉"
    },
    {
      "name_kr": "박성중",
      "party": "새누리당",
      "name_cn": "朴成重"
    },
    {
      "name_kr": "박순자",
      "party": "새누리당",
      "name_cn": "朴順子"
    },
    {
      "name_kr": "유민봉",
      "party": "새누리당",
      "name_cn": "庾敏鳳"
    },
    {
      "name_kr": "이명수",
      "party": "새누리당",
      "name_cn": "李明洙"
    },
    {
      "name_kr": "이완영",
      "party": "새누리당",
      "name_cn": "李完永"
    },
    {
      "name_kr": "이헌승",
      "party": "새누리당",
      "name_cn": "李憲昇"
    },
    {
      "name_kr": "주광덕",
      "party": "새누리당",
      "name_cn": "朱光德"
    },
    {
      "name_kr": "홍철호",
      "party": "새누리당",
      "name_cn": "洪哲鎬"
    },
    {
      "name_kr": "황영철",
      "party": "새누리당",
      "name_cn": "黃永哲"
    }
  ],
  "summaries": [
    "\n제안이유 및 주요내용\n\n  현재 시설물의 안전관리는 「시설물의 안전관리에 관한 특별법」 및 「재난 및 안전관리 기본법」에 따라 국토교통부와 국민안전처로 이원화되어 있음. 이와 같은 시설물 안전관리체계의 이원화는 실제 사고 발생 시 대응체계의 혼선 등 여러 가지 문제점을 드러내고 있음.\n  이에 현행법상의 특정관리대상시설을 「시설물의 안전관리에 관한 특별법」의 제3종시설로 규정하여 시설물의 안전관리 소관 부처를 국토교통부로 일원화함으로써 시설물에 대한 안전관리를 강화하고자 함(안 제27조 및 제28조 삭제).\n\n\n참고사항\n\n  이 법률안은 이우현의원이 대표발의한 「시설물의 안전관리에 관한 특별법 전부개정법률안」(의안번호 제1973호)의 의결을 전제로 하는 것이므로 같은 법률안이 의결되지 아니하거나 수정의결되는 경우에는 이에 맞추어 조정되어야 할 것임.\n"
  ],
  "withdrawers": [],
  "proposed_date": "2016-10-21",
  "decision_date": "2016-12-29",
  "link_id": "PRC_M1L6P1R0J2A1Z1B4W1U2S5U4H5F9H6",
  "proposer_type": "의원",
  "status": "처리"
}