{
  "assembly_id": 20,
  "bill_id": "2002116",
  "title": "[2002116] 수출용 원재료에 대한 관세 등 환급에 관한 특례법 일부개정법률안(정부) 입법예고중",
  "current_status": "공포",
  "reception_info": [
    "2002116",
    "2016-09-02",
    "정부",
    "의안원문",
    "제20대 (2016~2020) 제346회"
  ],
  "reception_file_link": "javascript:openBillFile('http://likms.assembly.go.kr/filegate/servlet/FileGate','B7E182D5-D04B-E92C-1A03-72CBBA688204','0');",
  "proposers": [],
  "summaries": [
    "\n■ 제안이유 및 주요내용 \n\n  납세의무자가 가격신고를 할 때 신고하여야 할 가격이 확정되지 아니하여 잠정가격으로 신고한 이후 확정된 가격을 신고받거나 가격을 확정한 경우에는, 잠정가격을 기초로 신고납부한 세액과 확정된 가격에 따른 세액의 차액으로서 징수하여야 하는 금액을 해당 납세의무자에 대하여 결정한 환급금으로 충당할 수 있도록 함으로써 납세편의 제고 및 납세협력 비용 절감을 도모할 수 있도록 하려는 것임.\n"
  ],
  "withdrawers": [],
  "proposed_date": "2016-09-02",
  "decision_date": "2016-12-08",
  "link_id": "ARC_Y1X6H0R9Y0I2F2U0F3Z1T0N7C3Z4X2",
  "proposer_type": "정부",
  "status": "처리"
}