{
  "assembly_id": 20,
  "bill_id": "2003331",
  "title": "[2003331] 평생교육법 일부개정법률안(신보라의원 등 12인) 입법예고중",
  "current_status": "위원회 심사",
  "reception_info": [
    "2003331",
    "2016-11-07",
    "신보라의원 등 12인",
    "의안원문\n비용추계서",
    "제20대 (2016~2020) 제346회"
  ],
  "reception_file_link": "javascript:openBillFile('http://likms.assembly.go.kr/filegate/servlet/FileGate','120639D7-1FB3-A9E7-FFFA-A7B9AD67E9E4','0');",
  "proposers": [
    {
      "name_kr": "신보라",
      "party": "새누리당",
      "name_cn": "申普羅"
    },
    {
      "name_kr": "경대수",
      "party": "새누리당",
      "name_cn": "慶大秀"
    },
    {
      "name_kr": "김선동",
      "party": "새누리당",
      "name_cn": "金善東"
    },
    {
      "name_kr": "김성태",
      "party": "새누리당",
      "name_cn": "金聖泰"
    },
    {
      "name_kr": "박덕흠",
      "party": "새누리당",
      "name_cn": "朴德欽"
    },
    {
      "name_kr": "송희경",
      "party": "새누리당",
      "name_cn": "宋喜卿"
    },
    {
      "name_kr": "윤종필",
      "party": "새누리당",
      "name_cn": "尹鍾畢"
    },
    {
      "name_kr": "장석춘",
      "party": "새누리당",
      "name_cn": "張錫春"
    },
    {
      "name_kr": "전희경",
      "party": "새누리당",
      "name_cn": "全希卿"
    },
    {
      "name_kr": "조경태",
      "party": "새누리당",
      "name_cn": "趙慶泰"
    },
    {
      "name_kr": "하태경",
      "party": "새누리당",
      "name_cn": "河泰慶"
    },
    {
      "name_kr": "함진규",
      "party": "새누리당",
      "name_cn": "咸珍圭"
    }
  ],
  "summaries": [
    "\n■ 제안이유 및 주요내용 \n\n  현행법은 학력인정 평생교육시설에 교원을 둘 수 있도록 규정하고 있음.\n  현재 2016년 4월 기준으로 학력인정 평생교육시설에 다니고 있는 20세 이하 청소년 수는 14,127명에 이르고, 이들 학생 대부분이 정규교육과정을 중단한 학생들로 학교폭력, 집단따돌림, 가정폭력 등에 노출될 가능성이 높은 상황인데도 이들을 전문적으로 상담해 주는 교사가 전무한 실정임.\n  이에 학력인정 평생교육시설에 전문상담교사를 둘 수 있는 명시적인 규정을 마련함으로써 학교생활 부적응 및 정서적 위기학생들에게 적합한 서비스를 제공하는 데 기여하려는 것임(안 제31조의2 신설).\n"
  ],
  "withdrawers": [],
  "proposed_date": "2016-11-07",
  "decision_date": null,
  "link_id": "PRC_I1J6E1T1E0O7G1J4U0R0Q3H6J0W7J1",
  "proposer_type": "의원",
  "status": "처리"
}