{
  "assembly_id": 20,
  "bill_id": "2005922",
  "title": "[2005922] 법령 등 공포에 관한 법률 일부개정법률안(신동근의원 등 17인) 입법예고중",
  "current_status": "대안반영폐기",
  "reception_info": [
    "2005922",
    "2017-03-02",
    "신동근의원 등 17인",
    "의안원문",
    "제20대 (2016~2020) 제349회"
  ],
  "reception_file_link": "javascript:openBillFile('http://likms.assembly.go.kr/filegate/servlet/FileGate','E2516A60-F0F5-5CF8-8615-63B4A8F6205F','0');",
  "proposers": [
    {
      "name_kr": "신동근",
      "party": "더불어민주당",
      "name_cn": "申東根"
    },
    {
      "name_kr": "김영춘",
      "party": "더불어민주당",
      "name_cn": "金榮春"
    },
    {
      "name_kr": "김영호",
      "party": "더불어민주당",
      "name_cn": "金映豪"
    },
    {
      "name_kr": "노웅래",
      "party": "더불어민주당",
      "name_cn": "盧雄來"
    },
    {
      "name_kr": "도종환",
      "party": "더불어민주당",
      "name_cn": "都鐘煥"
    },
    {
      "name_kr": "박홍근",
      "party": "더불어민주당",
      "name_cn": "朴洪根"
    },
    {
      "name_kr": "설훈",
      "party": "더불어민주당",
      "name_cn": "薛勳"
    },
    {
      "name_kr": "손혜원",
      "party": "더불어민주당",
      "name_cn": "孫惠園"
    },
    {
      "name_kr": "신창현",
      "party": "더불어민주당",
      "name_cn": "申昌賢"
    },
    {
      "name_kr": "안민석",
      "party": "더불어민주당",
      "name_cn": "安敏錫"
    },
    {
      "name_kr": "오영훈",
      "party": "더불어민주당",
      "name_cn": "吳怜勳"
    },
    {
      "name_kr": "이개호",
      "party": "더불어민주당",
      "name_cn": "李介昊"
    },
    {
      "name_kr": "이용득",
      "party": "더불어민주당",
      "name_cn": "李龍得"
    },
    {
      "name_kr": "이해찬",
      "party": "더불어민주당",
      "name_cn": "李海瓚"
    },
    {
      "name_kr": "전재수",
      "party": "더불어민주당",
      "name_cn": "田載秀"
    },
    {
      "name_kr": "조승래",
      "party": "더불어민주당",
      "name_cn": "趙承來"
    },
    {
      "name_kr": "홍의락",
      "party": "무소속",
      "name_cn": "洪宜洛"
    }
  ],
  "summaries": [
    "\n제안이유 및 주요내용\n\n  현행법상 법령 등의 공포는 관보에 게재함으로써 하고, 그 관보는 종이관보가 기본임. 이와 관련 판례(대구고법 1974.10.10. 72노244 형사부판결)는 법령 등의 공포의 효력이 발생하기 위해서는 적어도 관보가 일반 국민이 열독할 수 있는 상태에 놓여야 할 필요가 있다고 판시하고 있음.\n  그러나 종이관보는 인쇄에 일정 시간을 요하여 이를 통한 법령 등의 공포는 입법자의 의도와 달리 그 효력 발생을 지연시키는 요인이 되고 있음. 또한, 법령 등의 공포가 그 법령의 내용을 일반 국민에게 알리기 위한 표시행위라는 점을 감안할 때 정보통신기술의 발달로 이를 보다 효과적으로 할 수 있는 전자관보를 종이관보보다 우선할 필요가 있음.\n  이에 법령 등의 공포 방식을 전자관보를 기본으로 하고, 종이관보를 보완적으로 운영함으로써, 법령 등의 효력 발생의 불필요한 지연을 예방하고, 국민의 알권리를 강화하고자 함(안 제11조 및 제12조).\n"
  ],
  "withdrawers": [],
  "proposed_date": "2017-03-02",
  "decision_date": "2018-09-20",
  "link_id": "PRC_X1M7S0D3E0P2X1E0H5V1F3G5K6D7J9",
  "proposer_type": "의원",
  "status": "처리"
}