{
  "assembly_id": 20,
  "bill_id": "2006306",
  "title": "[2006306] 청소년 보호법 일부개정법률안(정우택의원 등 12인) 입법예고중",
  "current_status": "위원회 심사",
  "reception_info": [
    "2006306",
    "2017-03-21",
    "정우택의원 등 12인",
    "의안원문",
    "제20대 (2016~2020) 제350회"
  ],
  "reception_file_link": "javascript:openBillFile('http://likms.assembly.go.kr/filegate/servlet/FileGate','F8772929-51BB-B97D-E583-1246A581E362','0');",
  "proposers": [
    {
      "name_kr": "정우택",
      "party": "자유한국당",
      "name_cn": "鄭宇澤"
    },
    {
      "name_kr": "강효상",
      "party": "자유한국당",
      "name_cn": "姜孝祥"
    },
    {
      "name_kr": "권석창",
      "party": "자유한국당",
      "name_cn": "權錫昌"
    },
    {
      "name_kr": "김석기",
      "party": "자유한국당",
      "name_cn": "金碩基"
    },
    {
      "name_kr": "김선동",
      "party": "자유한국당",
      "name_cn": "金善東"
    },
    {
      "name_kr": "김성태",
      "party": "자유한국당",
      "name_cn": "金成泰"
    },
    {
      "name_kr": "유기준",
      "party": "자유한국당",
      "name_cn": "兪奇濬"
    },
    {
      "name_kr": "윤종필",
      "party": "자유한국당",
      "name_cn": "尹鍾畢"
    },
    {
      "name_kr": "윤한홍",
      "party": "자유한국당",
      "name_cn": "尹漢洪"
    },
    {
      "name_kr": "장제원",
      "party": "바른정당",
      "name_cn": "張濟元"
    },
    {
      "name_kr": "정갑윤",
      "party": "무소속",
      "name_cn": "鄭甲潤"
    },
    {
      "name_kr": "정용기",
      "party": "자유한국당",
      "name_cn": "鄭容起"
    }
  ],
  "summaries": [
    "\n■ 제안이유 및 주요내용 \n\n  현행법은 성매매 전단지 등 청소년유해매체물에 해당하는 옥외광고물을 공공장소에 공공연하게 설치·부착 또는 배포하는 행위를 금지하고 있음.\n  그러나 청소년유해매체물에 해당하는 옥외광고물이 공공장소에 부착 또는 배포되는 것을 실시간으로 적발·단속하는 것에는 현실적으로 한계가 있고, 이러한 옥외광고물을 통해 불건전한 교제를 조장·매개하거나 성매매 등을 유발할 우려가 있는 서비스의 이용을 알선하는 전화번호가 청소년에게 무분별하게 노출되고 있는 실정임.\n  이에 여성가족부장관, 시장·군수·구청장 및 관할 경찰서장 등이 청소년유해매체물에 해당하는 옥외광고물이 공공장소에 설치·부착 또는 배포되고 있는 것을 발견한 때에는 전기통신사업자에게 해당 옥외광고물에 게재된 전화번호 회선에 대한 전기통신역무 제공의 중지를 요청할 수 있도록 하여 불법·음란 서비스 등의 이용을 알선·조장하는 전화번호 회선을 신속하게 차단하고 청소년을 유해한 환경으로부터 보호하려는 것임(안 제19조의2 신설 및 제31조제1항).\n"
  ],
  "withdrawers": [],
  "proposed_date": "2017-03-21",
  "decision_date": null,
  "link_id": "PRC_W1A7Q0F3Y2B1E1A0S3B5H1Z0I9R3P0",
  "proposer_type": "의원",
  "status": "처리"
}