{
  "assembly_id": 20,
  "bill_id": "2007940",
  "title": "[2007940] 하도급거래 공정화에 관한 법률 일부개정법률안(김기선의원 등 18인) 입법예고중",
  "current_status": "위원회 심사",
  "reception_info": [
    "2007940",
    "2017-07-12",
    "김기선의원 등 18인",
    "의안원문",
    "제20대 (2016~2020) 제352회"
  ],
  "reception_file_link": "javascript:openBillFile('http://likms.assembly.go.kr/filegate/servlet/FileGate','69DAC38B-2319-E3D5-8049-96756055411B','0');",
  "proposers": [
    {
      "name_kr": "김기선",
      "party": "자유한국당",
      "name_cn": "金起善"
    },
    {
      "name_kr": "김상훈",
      "party": "자유한국당",
      "name_cn": "金相勳"
    },
    {
      "name_kr": "김성태",
      "party": "자유한국당",
      "name_cn": "金聖泰"
    },
    {
      "name_kr": "문진국",
      "party": "자유한국당",
      "name_cn": "文鎭國"
    },
    {
      "name_kr": "박대출",
      "party": "자유한국당",
      "name_cn": "朴大出"
    },
    {
      "name_kr": "송석준",
      "party": "자유한국당",
      "name_cn": "宋錫俊"
    },
    {
      "name_kr": "유기준",
      "party": "자유한국당",
      "name_cn": "兪奇濬"
    },
    {
      "name_kr": "이명수",
      "party": "자유한국당",
      "name_cn": "李明洙"
    },
    {
      "name_kr": "이양수",
      "party": "자유한국당",
      "name_cn": "李亮壽"
    },
    {
      "name_kr": "이완영",
      "party": "자유한국당",
      "name_cn": "李完永"
    },
    {
      "name_kr": "이우현",
      "party": "자유한국당",
      "name_cn": "李愚鉉"
    },
    {
      "name_kr": "이주영",
      "party": "자유한국당",
      "name_cn": "李柱榮"
    },
    {
      "name_kr": "임이자",
      "party": "자유한국당",
      "name_cn": "林利子"
    },
    {
      "name_kr": "장제원",
      "party": "자유한국당",
      "name_cn": "張濟元"
    },
    {
      "name_kr": "정성호",
      "party": "더불어민주당",
      "name_cn": "鄭成湖"
    },
    {
      "name_kr": "정태옥",
      "party": "자유한국당",
      "name_cn": "鄭泰沃"
    },
    {
      "name_kr": "최교일",
      "party": "자유한국당",
      "name_cn": "崔敎一"
    },
    {
      "name_kr": "추경호",
      "party": "자유한국당",
      "name_cn": "秋慶鎬"
    }
  ],
  "summaries": [
    "\n■ 제안이유 및 주요내용 \n  현행법은 발주자와 원사업자 그리고 수급사업자간의 하도급거래에 관한 사항을 규정하고 있으나, 수급사업자가 제조등의 위탁을 수행하는 도중에 발주자로부터 직접 추가적인 위탁을 받는 때에는 수급사업자 보호가 어려운 면이 있음.\n  원사업자는 추가적인 위탁을 한 당사자가 아니므로 추가대금의 지급을 거절하고, 발주자는 수급사업자의 직접 계약 당사자가 아니므로 계약에 따른 책임을 묻기 어려운 실정임.\n  이에 발주자가 직접 추가적인 제조등의 위탁을 한 경우 하도급대금의 직접 지급을 하도록 함으로써 수급사업자를 두텁게 보호하고자 함(안 제14조제1항제5호 신설).\n"
  ],
  "withdrawers": [],
  "proposed_date": "2017-07-12",
  "decision_date": null,
  "link_id": "PRC_E1A7H0P7M1X2L1H0B4L0Z0E6J7A8R7",
  "proposer_type": "의원",
  "status": "처리"
}