{
  "assembly_id": 20,
  "bill_id": "2011327",
  "title": "[2011327] 소금산업 진흥법 일부개정법률안(이명수의원 등 10인) 입법예고중",
  "current_status": "대안반영폐기",
  "reception_info": [
    "2011327",
    "2018-01-09",
    "이명수의원 등 10인",
    "의안원문",
    "제20대 (2016~2020) 제355회"
  ],
  "reception_file_link": "javascript:openBillFile('http://likms.assembly.go.kr/filegate/servlet/FileGate','5D65EAA8-E761-1199-0D7B-6A214EB1712F','0');",
  "proposers": [
    {
      "name_kr": "이명수",
      "party": "자유한국당",
      "name_cn": "李明洙"
    },
    {
      "name_kr": "강효상",
      "party": "자유한국당",
      "name_cn": "姜孝祥"
    },
    {
      "name_kr": "김명연",
      "party": "자유한국당",
      "name_cn": "金明淵"
    },
    {
      "name_kr": "김성찬",
      "party": "자유한국당",
      "name_cn": "金盛贊"
    },
    {
      "name_kr": "김재원",
      "party": "자유한국당",
      "name_cn": "金在原"
    },
    {
      "name_kr": "박인숙",
      "party": "바른정당",
      "name_cn": "朴仁淑"
    },
    {
      "name_kr": "성일종",
      "party": "자유한국당",
      "name_cn": "成一鍾"
    },
    {
      "name_kr": "윤한홍",
      "party": "자유한국당",
      "name_cn": "尹漢洪"
    },
    {
      "name_kr": "이정현",
      "party": "무소속",
      "name_cn": "李貞鉉"
    },
    {
      "name_kr": "함진규",
      "party": "자유한국당",
      "name_cn": "咸珍圭"
    }
  ],
  "summaries": [
    "\n제안이유 및 주요내용\n\n  현행법 제17조제3항에서 “「전자거래기본법」 제2조제5호에 따른 전자거래”로 규정되어 있으나, 「전자거래기본법」은 2012년에 「전자문서 및 전자거래 기본법」으로 개정되었음. 그러나 여전히 개정 이전 법률명으로 규정되어 있어 국민들에게 혼란을 줄 우려가 있음.\n  따라서 “「전자거래기본법」”을 “「전자문서 및 전자거래 기본법」”으로 개정하여 혼란을 없애고자 함(안 제17조제3항).\n"
  ],
  "withdrawers": [],
  "proposed_date": "2018-01-09",
  "decision_date": "2018-11-23",
  "link_id": "PRC_Z1C8N0V1W0J9J1C5M3A9G0S9X4O4I5",
  "proposer_type": "의원",
  "status": "처리"
}