{
  "assembly_id": 20,
  "bill_id": "2012485",
  "title": "[2012485] 주택법 일부개정법률안(박인숙의원 등 10인) 입법예고중",
  "current_status": "위원회 심사",
  "reception_info": [
    "2012485",
    "2018-03-15",
    "박인숙의원 등 10인",
    "의안원문",
    "제20대 (2016~2020) 제358회"
  ],
  "reception_file_link": "javascript:openBillFile('http://likms.assembly.go.kr/filegate/servlet/FileGate','D32CFEE6-6A26-857B-080C-74D2414D3AD4','0');",
  "proposers": [
    {
      "name_kr": "박인숙",
      "party": "자유한국당",
      "name_cn": "朴仁淑"
    },
    {
      "name_kr": "강석진",
      "party": "자유한국당",
      "name_cn": "姜錫振"
    },
    {
      "name_kr": "김명연",
      "party": "자유한국당",
      "name_cn": "金明淵"
    },
    {
      "name_kr": "김상훈",
      "party": "자유한국당",
      "name_cn": "金相勳"
    },
    {
      "name_kr": "김석기",
      "party": "자유한국당",
      "name_cn": "金碩基"
    },
    {
      "name_kr": "김성원",
      "party": "자유한국당",
      "name_cn": "金成願"
    },
    {
      "name_kr": "김현아",
      "party": "자유한국당",
      "name_cn": "金炫我"
    },
    {
      "name_kr": "유승민",
      "party": "바른미래당",
      "name_cn": "劉承旼"
    },
    {
      "name_kr": "이명수",
      "party": "자유한국당",
      "name_cn": "李明洙"
    },
    {
      "name_kr": "이현재",
      "party": "자유한국당",
      "name_cn": "李賢在"
    }
  ],
  "summaries": [
    "\n제안이유 및 주요내용\n\n  현행 「주택건설기준 등에 관한 규정」은 외부공기 유입을 목적으로 설치된 통로 또는 공간에 면한 부위에 난간을 설치하는 공동주택에 각 세대마다 1개소 이상의 국기를 꽂을 수 있는 장치를 해당 난간에 설치하도록 규정하고 있음.\n  그런데 안전유리 등으로 난간이 설치된 초고층 아파트와 주상복합 건축물 등의 경우 국기를 꽂을 수 있는 장치를 외부에 설치할 근거가 마련되어 있지 않아 역사와 전통, 국권·국위·존엄성을 나타내는 대표적인 상징인 국기의 활용이 활성화되기 어려운 상황임.\n  이에 사업주체가 공동주택의 옥외에 난간을 설치하는 경우 국기를 꽂을 수 있는 시설을 설치하여 입주민들이 국경일 등의 국기게양에 적극 동참하도록 함으로써 우리나라의 역사와 전통 및 이상이 담겨져 있는 국기에 대한 국민들의 자긍심을 제고시키고 애국정신을 고양하려는 것임(안 제40조의2 신설).\n"
  ],
  "withdrawers": [],
  "proposed_date": "2018-03-15",
  "decision_date": null,
  "link_id": "PRC_T1X8H0E3C1T5S1U4C2D4C2M4L4H5B6",
  "proposer_type": "의원",
  "status": "처리"
}