{
  "assembly_id": 20,
  "bill_id": "2012686",
  "title": "[2012686] 농약관리법 일부개정법률안(박완주의원 등 12인) 입법예고중",
  "current_status": "대안반영폐기",
  "reception_info": [
    "2012686",
    "2018-03-27",
    "박완주의원 등 12인",
    "의안원문\n비용추계서",
    "제20대 (2016~2020) 제358회"
  ],
  "reception_file_link": "javascript:openBillFile('http://likms.assembly.go.kr/filegate/servlet/FileGate','287ED05E-DEEA-2819-492F-541CA562B318','0');",
  "proposers": [
    {
      "name_kr": "박완주",
      "party": "더불어민주당",
      "name_cn": "朴完柱"
    },
    {
      "name_kr": "강훈식",
      "party": "더불어민주당",
      "name_cn": "姜勳植"
    },
    {
      "name_kr": "김성수",
      "party": "더불어민주당",
      "name_cn": "金聖洙"
    },
    {
      "name_kr": "남인순",
      "party": "더불어민주당",
      "name_cn": "南仁順"
    },
    {
      "name_kr": "박정",
      "party": "더불어민주당",
      "name_cn": "朴釘"
    },
    {
      "name_kr": "박주민",
      "party": "더불어민주당",
      "name_cn": "朴柱民"
    },
    {
      "name_kr": "백혜련",
      "party": "더불어민주당",
      "name_cn": "白惠蓮"
    },
    {
      "name_kr": "신창현",
      "party": "더불어민주당",
      "name_cn": "申昌賢"
    },
    {
      "name_kr": "원혜영",
      "party": "더불어민주당",
      "name_cn": "元惠榮"
    },
    {
      "name_kr": "임종성",
      "party": "더불어민주당",
      "name_cn": "林鍾聲"
    },
    {
      "name_kr": "정성호",
      "party": "더불어민주당",
      "name_cn": "鄭成湖"
    },
    {
      "name_kr": "추미애",
      "party": "더불어민주당",
      "name_cn": "秋美愛"
    }
  ],
  "summaries": [
    "\n제안이유\n\n  현행법은 농약의 제조업자·수입업자 또는 판매업자에게 독성이 높은 농약 등을 구매한 구매자의 이름·주소·품목명·수량 등을 장부에 기재하고 3년간 보존하도록 하는 등 판매기록을 의무화하고 있음.\n  그러나 농촌 등에서 농약의 판매 및 구매가 자율적으로 이루어지면서 안전사용기준을 위반하여 농약을 사용하고 이로 인해 안전성이 부족한 농산물이 생산되는 사례가 자주 발생하고 있지만, 농약의 판매·구매 등과 관련하여 체계적인 이력관리는 미흡한 실정임.\n  이에 농촌진흥청장이 농약안전정보시스템을 구축·운영하여 올바른 농약 판매 및 사용을 유도하고 농약의 유통 및 구매에 대한 이력관리를 통해 농산물의 안전성 등을 확보하려는 것임.\n\n\n주요내용\n\n가. 농약의 제조업자·수입업자·판매업자·방제업자는 독성이 높은 농약 등 농림축산식품부령으로 정하는 농약을 판매한 경우 농약의 구매정보 등을 전자적으로 기록 및 보존하고 농촌진흥청장에게 제공하여야 함(안 제23조의2).\n나. 농촌진흥청장은 농약의 제조업·수입업·판매업·방제업의 등록 또는 신고와 관련된 정보 수집 및 관리 등의 업무를 수행하기 위하여 농약안전정보시스템을 구축·운영하여야 함(안 제23조의3제1항 신설).\n다. 농촌진흥청장은 직권에 의한 품목등록의 취소 등의 공표 외에 농약안전정보시스템으로 수집된 정보를 공개하여서는 아니 됨(안 제23조의3제4항 신설).\n"
  ],
  "withdrawers": [],
  "proposed_date": "2018-03-27",
  "decision_date": "2018-12-07",
  "link_id": "PRC_P1Q8K0V3Z2Z7D0O9N5P9S3T7O9C5H0",
  "proposer_type": "의원",
  "status": "처리"
}