{
  "assembly_id": 20,
  "bill_id": "2014360",
  "title": "[2014360] 조세특례제한법 일부개정법률안(강훈식의원 등 16인) 입법예고중",
  "current_status": "위원회 심사",
  "reception_info": [
    "2014360",
    "2018-07-12",
    "강훈식의원 등 16인",
    "의안원문\n비용추계서",
    "제20대 (2016~2020) 제361회"
  ],
  "reception_file_link": "javascript:openBillFile('http://likms.assembly.go.kr/filegate/servlet/FileGate','C12C571F-7CE3-9EE6-FE84-40BB1F4CB0C9','0');",
  "proposers": [
    {
      "name_kr": "강훈식",
      "party": "더불어민주당",
      "name_cn": "姜勳植"
    },
    {
      "name_kr": "권미혁",
      "party": "더불어민주당",
      "name_cn": "權美赫"
    },
    {
      "name_kr": "권칠승",
      "party": "더불어민주당",
      "name_cn": "權七勝"
    },
    {
      "name_kr": "김경협",
      "party": "더불어민주당",
      "name_cn": "金炅俠"
    },
    {
      "name_kr": "남인순",
      "party": "더불어민주당",
      "name_cn": "南仁順"
    },
    {
      "name_kr": "민홍철",
      "party": "더불어민주당",
      "name_cn": "閔洪喆"
    },
    {
      "name_kr": "소병훈",
      "party": "더불어민주당",
      "name_cn": "蘇秉勳"
    },
    {
      "name_kr": "송옥주",
      "party": "더불어민주당",
      "name_cn": "宋玉珠"
    },
    {
      "name_kr": "안호영",
      "party": "더불어민주당",
      "name_cn": "安浩永"
    },
    {
      "name_kr": "유동수",
      "party": "더불어민주당",
      "name_cn": "柳東秀"
    },
    {
      "name_kr": "윤후덕",
      "party": "더불어민주당",
      "name_cn": "尹厚德"
    },
    {
      "name_kr": "이동섭",
      "party": "바른미래당",
      "name_cn": "李銅燮"
    },
    {
      "name_kr": "이수혁",
      "party": "더불어민주당",
      "name_cn": "李秀赫"
    },
    {
      "name_kr": "이원욱",
      "party": "더불어민주당",
      "name_cn": "李元旭"
    },
    {
      "name_kr": "임종성",
      "party": "더불어민주당",
      "name_cn": "林鍾聲"
    },
    {
      "name_kr": "조승래",
      "party": "더불어민주당",
      "name_cn": "趙承來"
    }
  ],
  "summaries": [
    "\n제안이유 및 주요내용\n\n  현재 우리나라는 부가가치세 단일세율제를 채택하고 있는데, 이는 사업자의 사무 부담 및 세무행정 비용을 경감하는 장점이 있는 대신 납세자의 인적사정을 전혀 고려하지 않는 물세로서 역진부담 문제가 발생하는 단점이 있음. 이를 보완하고자 우리나라는 생필품 등을 중심으로 「부가가치세법」과 「조세특례제한법」에서 품목을 정하여 면세 혜택을 주고 있음.\n  그러나 초·중·고 학교와 유치원·보육시설 등에서 쓰이는 난방유 및 여성과 노인 등의 사회 진출을 촉진하고 가사 부담 등을 덜어주기 위한 소위 ‘가사도우미’ 용역, 발달장애·지연 상태의 영유아에게 반드시 제공되어야 하는 언어치료 용역 등은 서민들에게 반드시 필요한 재화·용역이면서도 해당 면세 범위에서 빠져 있는 상태임.\n  이에 위에 열거한 재화와 용역에 대하여 부가가치세를 면세하도록 함으로써 서민들의 부담을 경감하고 현행 부가가치세 제도의 사각지대를 해소하기 위한 것임(안 제106조제1항).\n"
  ],
  "withdrawers": [],
  "proposed_date": "2018-07-12",
  "decision_date": null,
  "link_id": "PRC_T1M8X0W7W1K2E1A4I2C3E2D6B2Q4U5",
  "proposer_type": "의원",
  "status": "처리"
}