{
  "assembly_id": 20,
  "bill_id": "2016845",
  "title": "[2016845] 연구개발특구의 육성에 관한 특별법 일부개정법률안(이상민의원 등 11인) 입법예고중",
  "current_status": "위원회 심사",
  "reception_info": [
    "2016845",
    "2018-11-28",
    "이상민의원 등 11인",
    "의안원문",
    "제20대 (2016~2020) 제364회"
  ],
  "reception_file_link": "javascript:openBillFile('http://likms.assembly.go.kr/filegate/servlet/FileGate','9F27B51B-BBEF-3C71-D62D-2BBF7536194A','0');",
  "proposers": [
    {
      "name_kr": "이상민",
      "party": "더불어민주당",
      "name_cn": "李相珉"
    },
    {
      "name_kr": "강훈식",
      "party": "더불어민주당",
      "name_cn": "姜勳植"
    },
    {
      "name_kr": "김두관",
      "party": "더불어민주당",
      "name_cn": "金斗官"
    },
    {
      "name_kr": "김병욱",
      "party": "더불어민주당",
      "name_cn": "金炳旭"
    },
    {
      "name_kr": "안민석",
      "party": "더불어민주당",
      "name_cn": "安敏錫"
    },
    {
      "name_kr": "어기구",
      "party": "더불어민주당",
      "name_cn": "魚基龜"
    },
    {
      "name_kr": "이규희",
      "party": "더불어민주당",
      "name_cn": "李揆熙"
    },
    {
      "name_kr": "이종걸",
      "party": "더불어민주당",
      "name_cn": "李鍾杰"
    },
    {
      "name_kr": "이철희",
      "party": "더불어민주당",
      "name_cn": "李哲熙"
    },
    {
      "name_kr": "전재수",
      "party": "더불어민주당",
      "name_cn": "田載秀"
    },
    {
      "name_kr": "정성호",
      "party": "더불어민주당",
      "name_cn": "鄭成湖"
    }
  ],
  "summaries": [
    "\n제안이유\n\n  융？복합이 일상적인 제4차 산업혁명 시대를 효율적이고 민첩하게 대응하고 첨단 과학기술의 발전을 통해 개발된 새로운 기술과 서비스가 제한적 시험·기술적 검증(이하 “실증”이라 함)을 거쳐 다양한 신산업이 활성화할 수 있도록 하기 위해서는 과감하고 획기적인 규제 특례제도의 도입이 필요함.\n  특별히, 산？학？연 등 지식 생산기관이 집적되어 상호 의존성에 근거한 연계를 통하여 혁신적인 신기술을 창출하여야 하는 연구개발특구는 신기술에 대한 실증을 통해 그 ‘완결성’을 제고할 필요성이 훨씬 큼.\n  이에, 이 법률안은 다양한 혁신주체들이 창의적이고 혁신적인 아이디어로 구현한 기술과 서비스가 활성화 될 수 있도록 연구개발특구 안에서 일시적으로 규제를 적용하지 않는 등 실증에 필요한 규제특례를 부여할 수 있는 법적 근거를 마련하려는 것임.\n\n\n주요내용\n\n가. 누구든지 특구 내에서 신기술 활성화를 위한 실증을 할 수 있고, 국민의 생명과 안전에 위해가 되거나 환경을 저해하는 경우에만 제한하는 원칙 등을 규정함(안 제3조의3 신설).\n나. 과학기술정보통신부장관이 실증을 위한 규제특례에 관한 사항을 전문적으로 심의하기 위하여 연구개발특구위원회의 심의·의결 사항을 신설하고, 이를 위한 제반 규정을 정비함(안 제7조).\n다. 허가 등의 근거가 되는 법령에 기준·규격·요건 등이 없거나 적용하는 것이 맞지 아니하는 경우 또는 다른 법령의 규정에 의하여 허가 등을 신청하는 것이 불가능한 경우 신기술 또는 신기술을 활용한 제품·서비스에 대한 실증을 하기 위하여 규제의 전부 또는 일부를 적용하지 않도록 하는 규제특례를 신청할 수 있도록 하고, 이를 관리？감독하는 제도를 도입함(안 제16조의2부터 제16조의4까지 신설).\n"
  ],
  "withdrawers": [],
  "proposed_date": "2018-11-28",
  "decision_date": null,
  "link_id": "PRC_V1M8X1H1S2Z8X1B1J0L9G3P1E8V5T5",
  "proposer_type": "의원",
  "status": "처리"
}