{
  "assembly_id": 20,
  "bill_id": "2017485",
  "title": "[2017485] 인터넷 멀티미디어 방송사업법 일부개정법률안(김선동의원 등 10인) 입법예고중",
  "current_status": "위원회 심사",
  "reception_info": [
    "2017485",
    "2018-12-11",
    "김선동의원 등 10인",
    "의안원문",
    "제20대 (2016~2020) 제364회"
  ],
  "reception_file_link": "javascript:openBillFile('http://likms.assembly.go.kr/filegate/servlet/FileGate','676F1C46-328F-67C1-2636-A7E7250BC7FE','0');",
  "proposers": [
    {
      "name_kr": "김선동",
      "party": "자유한국당",
      "name_cn": "金善東"
    },
    {
      "name_kr": "김규환",
      "party": "자유한국당",
      "name_cn": "金奎煥"
    },
    {
      "name_kr": "김용태",
      "party": "자유한국당",
      "name_cn": "金容兌"
    },
    {
      "name_kr": "김정재",
      "party": "자유한국당",
      "name_cn": "金汀才"
    },
    {
      "name_kr": "문진국",
      "party": "자유한국당",
      "name_cn": "文鎭國"
    },
    {
      "name_kr": "박성중",
      "party": "자유한국당",
      "name_cn": "朴成重"
    },
    {
      "name_kr": "신보라",
      "party": "자유한국당",
      "name_cn": "申普羅"
    },
    {
      "name_kr": "이종명",
      "party": "자유한국당",
      "name_cn": "李鍾明"
    },
    {
      "name_kr": "이종배",
      "party": "자유한국당",
      "name_cn": "李鍾培"
    },
    {
      "name_kr": "조훈현",
      "party": "자유한국당",
      "name_cn": "曺薰鉉"
    }
  ],
  "summaries": [
    "\n제안이유 및 주요내용\n\n  최근 인터넷 멀티미디어 방송 콘텐츠 사업자(이하 “콘텐츠사업자”라 한다) 중 다수의 사업자가 영업적자를 겪고 있으며, 이에 따라 콘텐츠사업자가 방송 콘텐츠 제작에 투자하는 비용이 감소하는 문제가 발생하고 있음.\n  이와 관련하여 인터넷 멀티미디어 방송 제공사업자 등 유료방송플랫폼을 운영하는 사업자가 우월적 지위를 이용하여 콘텐츠사업자가 제공하는 방송 콘텐츠에 대하여 적정한 대가를 지급하지 않고 있고, 그 결과 콘텐츠사업자가 경영 위기를 겪는다는 지적이 있음.\n  한국방송채널진흥협회의 ‘콘텐츠 진흥을 위한 방송채널(PP)산업 발전 방안(2017.12.)’에 의하면, “유료방송사는 갑(甲)의 지위를 이용, 을(乙)의 일반PP 콘텐츠 제작원가의 1/3만 지급”이라고 적시되어 있음. 방통위의 2016년 방송사업자 재산상황 공표집 등에서도 ‘PP 콘텐츠 투자는 1조 5,758억원이지만, 유료방송사는 5,213억원을 지급’하고 있는 현실을 알 수 있음.\n  PP(Program Provider, 방송채널사용사업자 또는 프로그램 공급자)는 유료방송사의 방송 불가 결정 시 곧바로 시장에서 퇴출되기 때문에 유료방송사가 일방적으로 정한 프로그램 사용료를 수용할 수밖에 없는 구조이기 때문에, PP의 콘텐츠 투자가 구조적으로 어려움이 있어 일반PP 콘텐츠의 다양성을 저해할 우려가 있음.\n  한편, 현행법에는 인터넷 멀티미디어 방송 제공사업자가 콘텐츠사업자에게 지급한 방송콘텐츠 공급 대가의 적정성과 관련된 규정은 존재하지 않는 상황임.\n  이에 과학기술정보통신부장관이 인터넷 멀티미디어 방송 제공사업을 재허가하는 경우, 방송 콘텐츠 공급의 대가로 콘텐츠사업자에게 지급한 금액의 적정성을 심사하도록 함으로써 인터넷 멀티미디어 방송 시장의 일자리 창출과 더불어 선순환적 산업 기반확보와 공정경쟁환경 조성에 기여하려는 것임(안 제5조의2제2항제3호 신설).\n"
  ],
  "withdrawers": [],
  "proposed_date": "2018-12-11",
  "decision_date": null,
  "link_id": "PRC_N1G8X1K2X1I1O1M0K1M8F1I4S5E3R2",
  "proposer_type": "의원",
  "status": "처리"
}