{
  "assembly_id": 20,
  "bill_id": "2020212",
  "title": "[2020212] 자본시장과 금융투자업에 관한 법률 일부개정법률안(송희경의원 등 12인) 입법예고중",
  "current_status": "위원회 심사",
  "reception_info": [
    "2020212",
    "2019-05-07",
    "송희경의원 등 12인",
    "의안원문",
    "제20대 (2016~2020) 제368회"
  ],
  "reception_file_link": "javascript:openBillFile('http://likms.assembly.go.kr/filegate/servlet/FileGate','EA9B60F4-63AF-64F8-B9AD-788CC5B08EA5','0');",
  "proposers": [
    {
      "name_kr": "송희경",
      "party": "자유한국당",
      "name_cn": "宋喜卿"
    },
    {
      "name_kr": "김석기",
      "party": "자유한국당",
      "name_cn": "金碩基"
    },
    {
      "name_kr": "김태흠",
      "party": "자유한국당",
      "name_cn": "金泰欽"
    },
    {
      "name_kr": "김현아",
      "party": "자유한국당",
      "name_cn": "金炫我"
    },
    {
      "name_kr": "민경욱",
      "party": "자유한국당",
      "name_cn": "閔庚旭"
    },
    {
      "name_kr": "신보라",
      "party": "자유한국당",
      "name_cn": "申普羅"
    },
    {
      "name_kr": "이은권",
      "party": "자유한국당",
      "name_cn": "李殷權"
    },
    {
      "name_kr": "이종배",
      "party": "자유한국당",
      "name_cn": "李鍾培"
    },
    {
      "name_kr": "임이자",
      "party": "자유한국당",
      "name_cn": "林利子"
    },
    {
      "name_kr": "정갑윤",
      "party": "자유한국당",
      "name_cn": "鄭甲潤"
    },
    {
      "name_kr": "정운천",
      "party": "바른미래당",
      "name_cn": "鄭雲天"
    },
    {
      "name_kr": "조훈현",
      "party": "자유한국당",
      "name_cn": "曺薰鉉"
    }
  ],
  "summaries": [
    "\n제안이유 및 주요내용\n\n  현행법은 1억원 이상의 소득요건을 갖춘 투자자의 경우 온라인소액투자중개업을 통한 펀딩 금액을 ‘동일 온라인소액증권발행인에 대한 누적투자금액’은 1천만원 이하로서 대통령령으로 정하는 금액, ‘연간 총 누적투자금액’은 2천만원 이하로서 대통령령으로 정하는 금액으로 각각 일률적으로 제한하여 투자여력이 되는 투자자의 투자까지 제한한다는 비판이 있음.\n  이에 ‘동일 온라인소액증권발행인에 대한 누적투자금액’은 1천만원 이하로서 대통령령으로 정하는 금액 또는 연간 총소득금액의 100분의 5 이하로서 대통령령으로 정하는 금액 중 높은 금액, ‘연간 총 누적투자금액’은 2천만원 이하로서 대통령령으로 정하는 금액 또는 연간 총소득금액의 100분의 10 이하로서 대통령령으로 정하는 금액 중 높은 금액으로 각각 변경하여 온라인소액투자를 통한 자본시장 활성화를 달성하고자 하는 것임(안 제117조의10).\n"
  ],
  "withdrawers": [],
  "proposed_date": "2019-05-07",
  "decision_date": null,
  "link_id": "PRC_R1S9J0P5S0L7T1Z1P0J7V0K3V4K5O4",
  "proposer_type": "의원",
  "status": "처리"
}