{
  "assembly_id": 20,
  "bill_id": "2020776",
  "title": "[2020776] 물관리기본법  일부개정법률안(주승용의원 등 11인) 입법예고중",
  "current_status": "위원회 심사",
  "reception_info": [
    "2020776",
    "2019-06-03",
    "주승용의원 등 11인",
    "의안원문\n비용추계서",
    "제20대 (2016~2020) 제368회"
  ],
  "reception_file_link": "javascript:openBillFile('http://likms.assembly.go.kr/filegate/servlet/FileGate','BCF37F55-FF5D-2977-454B-77DF33788F08','0');",
  "proposers": [
    {
      "name_kr": "주승용",
      "party": "바른미래당",
      "name_cn": "朱昇鎔"
    },
    {
      "name_kr": "김관영",
      "party": "바른미래당",
      "name_cn": "金寬永"
    },
    {
      "name_kr": "김동철",
      "party": "바른미래당",
      "name_cn": "金東喆"
    },
    {
      "name_kr": "박광온",
      "party": "더불어민주당",
      "name_cn": "朴洸瑥"
    },
    {
      "name_kr": "유승희",
      "party": "더불어민주당",
      "name_cn": "兪承希"
    },
    {
      "name_kr": "윤영일",
      "party": "무소속",
      "name_cn": "尹英壹"
    },
    {
      "name_kr": "이동섭",
      "party": "바른미래당",
      "name_cn": "李銅燮"
    },
    {
      "name_kr": "임재훈",
      "party": "바른미래당",
      "name_cn": "林哉勳"
    },
    {
      "name_kr": "장정숙",
      "party": "바른미래당",
      "name_cn": "張貞淑"
    },
    {
      "name_kr": "최도자",
      "party": "바른미래당",
      "name_cn": "崔道子"
    },
    {
      "name_kr": "황주홍",
      "party": "민주평화당",
      "name_cn": "黃柱洪"
    }
  ],
  "summaries": [
    "\n제안이유 및 주요내용\n\n  현행법에 따르면 물관리에 관한 중요 사항을 심의·의결하기 위하여 대통령 소속으로 국가물관리위원회를 두고, 국가물관리위원회에 유역별로 유역물관리위원회를 두도록 규정되어 있음.\n  그런데 국가물관리위원회에는 사무국을 둘 수 있는 근거 규정이 있으나 유역물관리위원회에는 사무국에 대한 별도의 근거 규정이 없어 국가물관리위원회의 사무국에서 유역물관리위원회까지 운영하여야 하는 실정임.\n  이에 유역물관리위원회에 별도의 사무국을 두는 근거규정을 신설하여 물관리 현장 중심의 사무를 효율적으로 집행하려는 것임(안 제26조제5항).\n"
  ],
  "withdrawers": [],
  "proposed_date": "2019-06-03",
  "decision_date": null,
  "link_id": "PRC_L1P9O0V6N0N3E1E3N0V3M5K5Q7R8E4",
  "proposer_type": "의원",
  "status": "처리"
}