{
  "assembly_id": 20,
  "bill_id": "2020629",
  "title": "[2020629] 공연법 일부개정법률안(김수민의원 등 10인) 입법예고중",
  "current_status": "위원회 심사",
  "reception_info": [
    "2020629",
    "2019-05-24",
    "김수민의원 등 10인",
    "의안원문",
    "제20대 (2016~2020) 제368회"
  ],
  "reception_file_link": "javascript:openBillFile('http://likms.assembly.go.kr/filegate/servlet/FileGate','F70F516C-98C6-2AE4-5F5F-3B0C0CABD61A','0');",
  "proposers": [
    {
      "name_kr": "김수민",
      "party": "바른미래당",
      "name_cn": "金秀玟"
    },
    {
      "name_kr": "강길부",
      "party": "무소속",
      "name_cn": "姜吉夫"
    },
    {
      "name_kr": "김삼화",
      "party": "바른미래당",
      "name_cn": "金三和"
    },
    {
      "name_kr": "김종회",
      "party": "민주평화당",
      "name_cn": "金鍾懷"
    },
    {
      "name_kr": "김중로",
      "party": "바른미래당",
      "name_cn": "金中魯"
    },
    {
      "name_kr": "이동섭",
      "party": "바른미래당",
      "name_cn": "李銅燮"
    },
    {
      "name_kr": "이찬열",
      "party": "바른미래당",
      "name_cn": "李燦烈"
    },
    {
      "name_kr": "임재훈",
      "party": "바른미래당",
      "name_cn": "林哉勳"
    },
    {
      "name_kr": "정병국",
      "party": "바른미래당",
      "name_cn": "鄭柄國"
    },
    {
      "name_kr": "최도자",
      "party": "바른미래당",
      "name_cn": "崔道子"
    }
  ],
  "summaries": [
    "\n제안이유 및 주요내용\n\n  최근 K-POP, 드라마 등 한국을 대표하는 문화콘텐츠가 고부가가치산업으로 주목받아 왔으나 한류 콘텐츠의 획일적이고 식상함에 대한 지적이 제기됨에 따라 새로운 한류 콘텐츠로서 뮤지컬 등 공연예술이 주목받고 있음. \n  또한 현행법에 따르면 국가와 지방자치단체는 공연예술의 지역적 균형발전을 도모해야 함에도 불구하고 각 지방자치단체의 재정자립도, 지방자치단체장의 의지에 따라 지역별, 계층별 공연문화의 향유수준이 다르다는 지적이 있음. \n  이에 한국공연예술진흥원을 설립하여 한류의 지속적 성장을 도모할 수 있도록 공연예술 콘텐츠를 육성·지원하게 하고 공연예술 지원 인력을 양성하는 한편, 공연예술 소외계층과 소외지역에 대한 지원 등을 하게 하려는 것임(안 제17조 신설).\n"
  ],
  "withdrawers": [],
  "proposed_date": "2019-05-24",
  "decision_date": null,
  "link_id": "PRC_F1T9F0Z5M2Z4W1U5L3R0N3L1L2A8S0",
  "proposer_type": "의원",
  "status": "처리"
}