{
  "assembly_id": 20,
  "bill_id": "2022917",
  "title": "[2022917] 장사 등에 관한 법률 일부개정법률안(김순례의원 등 20인) 입법예고중",
  "current_status": "위원회 심사",
  "reception_info": [
    "2022917",
    "2019-10-18",
    "김순례의원 등 20인",
    "의안원문",
    "제20대 (2016~2020) 제371회"
  ],
  "reception_file_link": "javascript:openBillFile('http://likms.assembly.go.kr/filegate/servlet/FileGate','A726568C-0F37-E74B-E89E-9F32DBA0FE4F','0');",
  "proposers": [
    {
      "name_kr": "김순례",
      "party": "자유한국당",
      "name_cn": "金順禮"
    },
    {
      "name_kr": "강길부",
      "party": "무소속",
      "name_cn": "姜吉夫"
    },
    {
      "name_kr": "김두관",
      "party": "더불어민주당",
      "name_cn": "金斗官"
    },
    {
      "name_kr": "김석기",
      "party": "자유한국당",
      "name_cn": "金碩基"
    },
    {
      "name_kr": "김성원",
      "party": "자유한국당",
      "name_cn": "金成願"
    },
    {
      "name_kr": "김성태",
      "party": "자유한국당",
      "name_cn": "金成泰"
    },
    {
      "name_kr": "김재경",
      "party": "자유한국당",
      "name_cn": "金在庚"
    },
    {
      "name_kr": "문진국",
      "party": "자유한국당",
      "name_cn": "文鎭國"
    },
    {
      "name_kr": "백승주",
      "party": "자유한국당",
      "name_cn": "白承周"
    },
    {
      "name_kr": "신용현",
      "party": "바른미래당",
      "name_cn": "申容賢"
    },
    {
      "name_kr": "원유철",
      "party": "자유한국당",
      "name_cn": "元裕哲"
    },
    {
      "name_kr": "유민봉",
      "party": "자유한국당",
      "name_cn": "庾敏鳳"
    },
    {
      "name_kr": "윤영석",
      "party": "자유한국당",
      "name_cn": "尹永碩"
    },
    {
      "name_kr": "이언주",
      "party": "무소속",
      "name_cn": "李彦周"
    },
    {
      "name_kr": "이원욱",
      "party": "더불어민주당",
      "name_cn": "李元旭"
    },
    {
      "name_kr": "이은재",
      "party": "자유한국당",
      "name_cn": "李恩宰"
    },
    {
      "name_kr": "이헌승",
      "party": "자유한국당",
      "name_cn": "李憲昇"
    },
    {
      "name_kr": "정갑윤",
      "party": "자유한국당",
      "name_cn": "鄭甲潤"
    },
    {
      "name_kr": "정종섭",
      "party": "자유한국당",
      "name_cn": "鄭宗燮"
    },
    {
      "name_kr": "주호영",
      "party": "자유한국당",
      "name_cn": "朱豪英"
    }
  ],
  "summaries": [
    "\n제안이유 및 주요내용\n\n  현행법에 따르면 사설봉안시설을 설치·관리하려는 자는 그 사설봉안시설을 관할하는 시장 등에게 신고하도록 하고, 「국토의 계획 및 이용에 관한 법률」의 녹지지역 중 대통령령으로 정하는 지역, 「문화재보호법」에 따른 보호구역 등 봉안시설 등을 설치·조성할 수 없는 지역을 명시하고 있음.\n  그런데 「문화재보호법」에 따른 보호구역은 일정 규모 미만의 자연장지로서 문화재청장의 허가를 받은 경우 외에는 봉안시설을 설치할 수 없도록 함에 따라 문화재를 보유하고 있는 대다수의 사찰에서는 봉안시설을 설치하지 못하고 있는 상황임.\n  이에 종교단체에서 설치·관리하는 대통령령으로 정하는 규모 미만의 봉안시설로서 문화재를 훼손하지 않는 범위 내에서 봉안시설을 설치 할 수 있도록 예외를 마련하여 국토를 효율적으로 이용할 수 있도록 하려는 것임(안 제17조제3호 단서).\n"
  ],
  "withdrawers": [],
  "proposed_date": "2019-10-18",
  "decision_date": null,
  "link_id": "PRC_E1C9S1E0P1N8E1Q7N2J0B4F2M9B2G1",
  "proposer_type": "의원",
  "status": "처리"
}