{
  "assembly_id": 20,
  "bill_id": "2022652",
  "title": "[2022652] 마약류 불법거래 방지에 관한 특례법 일부개정법률안(김경협의원 등 11인) 입법예고중",
  "current_status": "위원회 심사",
  "reception_info": [
    "2022652",
    "2019-09-24",
    "김경협의원 등 11인",
    "의안원문",
    "제20대 (2016~2020) 제371회"
  ],
  "reception_file_link": "javascript:openBillFile('http://likms.assembly.go.kr/filegate/servlet/FileGate','7F23B082-6962-301B-3222-E967524B973C','0');",
  "proposers": [
    {
      "name_kr": "김경협",
      "party": "더불어민주당",
      "name_cn": "金炅俠"
    },
    {
      "name_kr": "강병원",
      "party": "더불어민주당",
      "name_cn": "姜炳遠"
    },
    {
      "name_kr": "기동민",
      "party": "더불어민주당",
      "name_cn": "奇東旻"
    },
    {
      "name_kr": "김현권",
      "party": "더불어민주당",
      "name_cn": "金玄權"
    },
    {
      "name_kr": "박홍근",
      "party": "더불어민주당",
      "name_cn": "朴洪根"
    },
    {
      "name_kr": "설훈",
      "party": "더불어민주당",
      "name_cn": "薛勳"
    },
    {
      "name_kr": "송옥주",
      "party": "더불어민주당",
      "name_cn": "宋玉珠"
    },
    {
      "name_kr": "신창현",
      "party": "더불어민주당",
      "name_cn": "申昌賢"
    },
    {
      "name_kr": "유승희",
      "party": "더불어민주당",
      "name_cn": "兪承希"
    },
    {
      "name_kr": "윤후덕",
      "party": "더불어민주당",
      "name_cn": "尹厚德"
    },
    {
      "name_kr": "이용득",
      "party": "더불어민주당",
      "name_cn": "李龍得"
    }
  ],
  "summaries": [
    "\n제안이유 및 주요내용 \n\n  현행법은 마약류 범죄의 발견 또는 불법수익 등의 출처에 관한 수사를 방해하거나 불법수익 등의 몰수를 회피할 목적으로 불법수익 등의 성질, 소재(所在), 출처 또는 귀속(歸屬) 관계를 숨기거나 가장(假裝)한 자에 대하여는 처벌하고 있으나 이러한 자를 위하여 자신의 명의를 대여한 자에 대하여는 별도의 처벌 규정을 두고 있지 않음.\n  불법수익 등을 은닉하거나 가장하려는 정황을 알면서도 적극적으로 자신의 명의를 대여한 자에 대하여 직접 법률에서 처벌할 수 있도록 함으로써 불법수익 관련 차명거래 행위를 추가적으로 차단·예방할 필요가 있음.\n  이에 불법수익 등을 은닉하거나 가장하려는 정황을 알면서도 금융거래에 자신의 명의를 대여한 자에 대하여도 처벌할 수 있도록 근거를 마련하려는 것임(안 제7조제4항 신설).\n"
  ],
  "withdrawers": [],
  "proposed_date": "2019-09-24",
  "decision_date": null,
  "link_id": "PRC_Y1Z9U0B9D2C4X1D7K5P0E5C8S1A3R6",
  "proposer_type": "의원",
  "status": "처리"
}