{
  "assembly_id": 20,
  "bill_id": "2022815",
  "title": "[2022815] 단결권 및 단체교섭 협약 비준동의안(정부) 입법예고중",
  "current_status": "위원회 심사",
  "reception_info": [
    "2022815",
    "2019-10-07",
    "정부",
    "의안원문",
    "제20대 (2016~2020) 제371회"
  ],
  "reception_file_link": "javascript:openBillFile('http://likms.assembly.go.kr/filegate/servlet/FileGate','0E995D23-936D-2C1A-03FD-695683D61975','0');",
  "proposers": [],
  "summaries": [
    "\n"
  ],
  "withdrawers": [],
  "proposed_date": "2019-10-07",
  "decision_date": null,
  "link_id": "PRC_K1Z9T1C0W0J7K1I0Y2Y4H0B3U5Q7X6",
  "proposer_type": "정부",
  "status": "처리"
}