{
  "assembly_id": 20,
  "bill_id": "2023304",
  "title": "[2023304] 지방세기본법 일부개정법률안(서영교의원 등 14인) 입법예고중",
  "current_status": "위원회 심사",
  "reception_info": [
    "2023304",
    "2019-10-30",
    "서영교의원 등 14인",
    "의안원문",
    "제20대 (2016~2020) 제371회"
  ],
  "reception_file_link": "javascript:openBillFile('http://likms.assembly.go.kr/filegate/servlet/FileGate','4F634648-B43E-2B9E-6479-A4450B1322E5','0');",
  "proposers": [
    {
      "name_kr": "서영교",
      "party": "더불어민주당",
      "name_cn": "徐瑛敎"
    },
    {
      "name_kr": "김경협",
      "party": "더불어민주당",
      "name_cn": "金炅俠"
    },
    {
      "name_kr": "김두관",
      "party": "더불어민주당",
      "name_cn": "金斗官"
    },
    {
      "name_kr": "김철민",
      "party": "더불어민주당",
      "name_cn": "金哲玟"
    },
    {
      "name_kr": "맹성규",
      "party": "더불어민주당",
      "name_cn": "孟聖奎"
    },
    {
      "name_kr": "백재현",
      "party": "더불어민주당",
      "name_cn": "白在鉉"
    },
    {
      "name_kr": "서형수",
      "party": "더불어민주당",
      "name_cn": "徐炯洙"
    },
    {
      "name_kr": "오제세",
      "party": "더불어민주당",
      "name_cn": "吳濟世"
    },
    {
      "name_kr": "윤일규",
      "party": "더불어민주당",
      "name_cn": "尹一逵"
    },
    {
      "name_kr": "이개호",
      "party": "더불어민주당",
      "name_cn": "李介昊"
    },
    {
      "name_kr": "인재근",
      "party": "더불어민주당",
      "name_cn": "印在謹"
    },
    {
      "name_kr": "정세균",
      "party": "더불어민주당",
      "name_cn": "丁世均"
    },
    {
      "name_kr": "조승래",
      "party": "더불어민주당",
      "name_cn": "趙承來"
    },
    {
      "name_kr": "홍영표",
      "party": "더불어민주당",
      "name_cn": "洪永杓"
    }
  ],
  "summaries": [
    "\n제안이유 및 주요내용\n\n  현재 지방자치단체는 경마장·경륜장 등에서 발생한 매출의 10%를 레저세로 징수하고 있으며, 이는 매출의 발생원천에 따라 본장 발생분과 장외 발생분으로 구분됨.\n  그런데 본장에서 발생하는 레저세는 본장이 소재한 지방자치단체에 전액 납부되는 반면, 장외발매소에서 발생하는 레저세의 경우 본장 소재 지방자치단체와 장외발매소 소재 지방자치단체에 분할 납부되고 있어 상대적으로 장외발매소 소재 지방자치단체의 세수가 적음.\n  또한, 레저세는 특별시·광역시·도세이므로 시·군·구가 민원, 교통혼잡, 소음 등 각종 사회적 비용을 실질적으로 부담하고 있음에도 불구하고 레저세 세입 중 시·군·구에 징수교부금과 조정교부금의 형식으로 배분되는 금액은 약 30%에 불과한 상황임.\n  이에 장외발매소가 있는 시·군·구에 신고·납부되는 레저세를 해당 시·군·구의 세목으로 이관함으로써 불합리한 과세체계를 개선하고 장외발매소로 인하여 시·군·구가 부담하고 있는 사회적 비용을 레저세 세입으로 보전할 수 있도록 하려는 것임(안 제11조의2 신설).\n"
  ],
  "withdrawers": [],
  "proposed_date": "2019-10-30",
  "decision_date": null,
  "link_id": "PRC_Z1U9I1R0Z3B0R1C7F3B5W4U4X0C8V4",
  "proposer_type": "의원",
  "status": "처리"
}